<?xml version="1.0" encoding="utf-8"?>
<DocProperty xmlns:xsi="http://www.w3.org/2001/XMLSchema-instance" id="CurrentToleranceLimit1_3G1sG0qVeHuO00025QrEV" Name="CurrentToleranceLimit1" UniqueId="3G1sG0qVeHuO00025QrE$V" PrimaryDataType="IfcTimeMeasure">
	<Localization>
		<DocLocalization Name="Current Tolerance Limit1" Locale="en" />
		<DocLocalization Name="許容電流限界1" Locale="ja-JP">
			<Documentation>許容電流1を制限する時間制限。
値が0の場合は、制限はない。</Documentation>
		</DocLocalization>
		<DocLocalization Name="허용전류한계1" Locale="ko-KR">
			<Documentation>허용 전류 1 제한 시간 제한. 값이 0이면 제한이 없다.</Documentation>
		</DocLocalization>
	</Localization>
</DocProperty>

