<?xml version="1.0" encoding="utf-8"?>
<DocPropertySet xmlns:xsi="http://www.w3.org/2001/XMLSchema-instance" Name="Pset_WasteTerminalTypeFloorTrap" UniqueId="1LJ480qXOHuO00025QrE$V" ApplicableType="IfcWasteTerminal/FLOORTRAP" PropertySetType="PSET_TYPEDRIVENOVERRIDE">
	<Localization>
		<DocLocalization Name="Waste Terminal Type Floor Trap" Locale="en" />
		<DocLocalization Locale="ja-JP">
			<Documentation>液体を溜めて汚れた空気の通過を防ぐために床に据えられる配管。</Documentation>
		</DocLocalization>
	</Localization>
	<Properties>
		<DocProperty xsi:nil="true" href="NominalBodyLength_1QgOo0qXOHuO00025QrEV" />
		<DocProperty xsi:nil="true" href="NominalBodyWidth_1Zcbu0qXOHuO00025QrEV" />
		<DocProperty xsi:nil="true" href="NominalBodyDepth_1hyfa0qXOHuO00025QrEV" />
		<DocProperty xsi:nil="true" href="IsForSullageWater_1rV040qXOHuO00025QrEV" />
		<DocProperty xsi:nil="true" href="SpilloverLevel_1yemy0qXOHuO00025QrEV" />
		<DocProperty xsi:nil="true" href="TrapType_25a_20qXOHuO00025QrEV" />
		<DocProperty xsi:nil="true" href="HasStrainer_2L4oc0qXOHuO00025QrEV" />
		<DocProperty xsi:nil="true" href="OutletConnectionSize_2SEZU0qXOHuO00025QrEV" />
		<DocProperty xsi:nil="true" href="InletPatternType_2cN3O0qXOHuO00025QrEV" />
		<DocProperty xsi:nil="true" href="InletConnectionSize_34APi0qXOHuO00025QrEV" />
		<DocProperty xsi:nil="true" href="CoverLength_3DimC0qXOHuO00025QrEV" />
		<DocProperty xsi:nil="true" href="CoverWidth_3MezI0qXOHuO00025QrEV" />
		<DocProperty xsi:nil="true" href="CoverMaterial_3VbAO0qXOHuO00025QrEV" />
	</Properties>
</DocPropertySet>

