<?xml version="1.0" encoding="utf-8"?>
<DocEntity xmlns:xsi="http://www.w3.org/2001/XMLSchema-instance" Name="IfcPreDefinedItem" UniqueId="24f52902-4123-41ea-bdd0-f47e6ab00191" BaseDefinition="IfcPresentationItem" EntityFlags="205">
	<Localization>
		<DocLocalization Locale="de" Name="Vordefiniertes Element" />
		<DocLocalization Locale="en" Name="Pre Defined Item" />
		<DocLocalization Locale="fr" Name="Item pré-défini" />
	</Localization>
	<Subtypes>
		<DocSubtype UniqueId="cff301cc-c27a-4c33-afb3-b1b929884149" DefinedType="IfcPreDefinedTextFont" />
		<DocSubtype UniqueId="63c46d64-0c74-4f9f-a4eb-430370639913" DefinedType="IfcPreDefinedColour" />
		<DocSubtype UniqueId="ef57c037-9a3f-47ac-945c-bf8ece370dd0" DefinedType="IfcPreDefinedCurveFont" />
	</Subtypes>
	<Attributes>
		<DocAttribute Name="Name" UniqueId="b0f1937f-94b4-4988-82a9-cf7620fca2ff" DefinedType="IfcLabel">
			<Documentation>The string by which the pre defined item is identified. Allowable values for the string are declared at the level of subtypes.</Documentation>
		</DocAttribute>
	</Attributes>
</DocEntity>

