<?xml version="1.0" encoding="utf-8"?>
<DocTemplateUsage xmlns:xsi="http://www.w3.org/2001/XMLSchema-instance" Name="Spatial Containment" UniqueId="1rMH_ly6b0JB7B0dxPBiDC">
	<Definition xsi:type="DocTemplateDefinition" xsi:nil="true" href="Spatial_Containment_1pwHycyvSaIO2cWa1vx6tU" />
	<Exchanges>
		<DocExchangeItem Applicability="export" Requirement="mandatory">
			<Exchange xsi:type="DocExchangeDefinition" xsi:nil="true" href="CV20Struct_1kIeNoAhrBGuKl0_ZzAQa0" />
		</DocExchangeItem>
		<DocExchangeItem Applicability="import" Requirement="mandatory">
			<Exchange xsi:type="DocExchangeDefinition" xsi:nil="true" href="CV20Import_only_2iQuwgxJtzI9lWDele7ZV1" />
		</DocExchangeItem>
	</Exchanges>
</DocTemplateUsage>

