<?xml version="1.0" encoding="utf-8"?>
<DocEnumeration xmlns:xsi="http://www.w3.org/2001/XMLSchema-instance" Name="IfcTimeSeriesScheduleTypeEnum" UniqueId="2otQy0m4v09QVIK6$O8LhW" DiagramNumber="1">
	<Constants>
		<DocConstant xsi:nil="true" href="ANNUAL_3LrU6xK21Ec8CLggigagkM" />
		<DocConstant xsi:nil="true" href="MONTHLY_3V4vwQQr1ARPtq6cT6NGBP" />
		<DocConstant xsi:nil="true" href="WEEKLY_2PgccEjwL0NuBLQ1JsBO0w" />
		<DocConstant xsi:nil="true" href="DAILY_10ytwWEfCjhdCP0YBP3l2" />
		<DocConstant xsi:nil="true" href="USERDEFINED_2v8q5jcH82x2hdLJed7YK" />
		<DocConstant xsi:nil="true" href="NOTDEFINED_1mb0bXOI98NwvlSy3R8Z5E" />
	</Constants>
</DocEnumeration>

