<?xml version="1.0" encoding="utf-8"?>
<DocDefined xmlns:xsi="http://www.w3.org/2001/XMLSchema-instance" Name="IfcPositivePlaneAngleMeasure" UniqueId="40cd7167-2011-405e-82f9-f6af73ed3182" DiagramNumber="2" DefinedType="IfcPlaneAngleMeasure" Length="0">
	<WhereRules>
		<DocWhereRule Name="WR1" UniqueId="3KTTm63ej4XuCrMgZ19rgA">
			<Documentation>A positive measure shall be greater than zero.</Documentation>
			<Expression>SELF &gt; 0.</Expression>
		</DocWhereRule>
	</WhereRules>
</DocDefined>

