<?xml version="1.0" encoding="utf-8"?>
<DocEnumeration xmlns:xsi="http://www.w3.org/2001/XMLSchema-instance" Name="IfcActionSourceTypeEnum" UniqueId="bfb08198-13c2-4fdb-8748-00a8b0d0b5e8" DiagramNumber="1">
	<Localization>
		<DocLocalization Name="Action Source Type Enum" Locale="en" />
		<DocLocalization Name="Énumération des types de source d&apos;action" Locale="fr" />
	</Localization>
	<DiagramRectangle xsi:type="DocRectangle" X="690.98842" Y="1235.2126" Width="404.86667" Height="54.05564" />
	<Constants>
		<DocConstant xsi:nil="true" href="DEAD_LOAD_G_1CpdJZEc5BUu7qt2FudjSe" />
		<DocConstant xsi:nil="true" href="COMPLETION_G1_0JH6hVpnrDAv6u82qH0smt" />
		<DocConstant xsi:nil="true" href="LIVE_LOAD_Q_1YjI1F2tHFs9bkS3Zwnw4i" />
		<DocConstant xsi:nil="true" href="SNOW_S_1Z0P6BCwnCTwgrfl504wPz" />
		<DocConstant xsi:nil="true" href="WIND_W_1kTqwYLT9zPpIEmhq0HGN" />
		<DocConstant xsi:nil="true" href="PRESTRESSING_P_1SbWTBWQH7SP4K6iERqWjp" />
		<DocConstant xsi:nil="true" href="SETTLEMENT_U_1uY0uFAIn7UxYaIdi9Rlo2" />
		<DocConstant xsi:nil="true" href="TEMPERATURE_T_2EFDu263T8qv4EC8UsO2IL" />
		<DocConstant xsi:nil="true" href="EARTHQUAKE_E_1CgMLvmJ92r8zFJmp3HcE" />
		<DocConstant xsi:nil="true" href="FIRE_0nT8xriqTCORwmV9zj7e4y" />
		<DocConstant xsi:nil="true" href="IMPULSE_2cpdpmpBD7Mx0607jw28IV" />
		<DocConstant xsi:nil="true" href="IMPACT_1oBdK0fMj1kwJgbs2UEgGy" />
		<DocConstant xsi:nil="true" href="TRANSPORT_1vuSeBkqHCe9K3DuAoVvn0" />
		<DocConstant xsi:nil="true" href="ERECTION_27k4lPNBrA2QG9PlVTa7tP" />
		<DocConstant xsi:nil="true" href="PROPPING_0PnxIf3Tz1mRZbHnvB9_um" />
		<DocConstant xsi:nil="true" href="SYSTEM_IMPERFECTION_17oGJ10HrC9Q9WbqHe3ZNb" />
		<DocConstant xsi:nil="true" href="SHRINKAGE_2wdxymnRPA4vXn5lnmwqYm" />
		<DocConstant xsi:nil="true" href="CREEP_0dLWYPcWLFN9gf4LLAfaeb" />
		<DocConstant xsi:nil="true" href="LACK_OF_FIT_0q91xN4qjAGOOduOzWAqzY" />
		<DocConstant xsi:nil="true" href="BUOYANCY_09K0sALuP0Jv0eBm2Bqyd" />
		<DocConstant xsi:nil="true" href="ICE_2YNRW9KnCGOoL5kaLiZnA" />
		<DocConstant xsi:nil="true" href="CURRENT_04TbO0qjD2a8ywaHB4FLpY" />
		<DocConstant xsi:nil="true" href="WAVE_0qhDkMVNL1OADjC4hm1_m" />
		<DocConstant xsi:nil="true" href="RAIN_1pboUg7avAhKGkdO_QCxF" />
		<DocConstant xsi:nil="true" href="BRAKES_0PECG06hTD5RDqyGFxIoov" />
		<DocConstant xsi:nil="true" href="USERDEFINED_0HOhZlQIX0gBDGrIOUixFQ" />
		<DocConstant xsi:nil="true" href="NOTDEFINED_3Qltahu3P5SRjovmonmhm" />
	</Constants>
</DocEnumeration>

