<?xml version="1.0" encoding="utf-8"?>
<DocTemplateUsage xmlns:xsi="http://www.w3.org/2001/XMLSchema-instance" UniqueId="3bLV_IZV994gukh1455nGw">
	<Definition xsi:type="DocTemplateDefinition" xsi:nil="true" href="Property_Sets_for_Objects_3tGbMc30vFCOIj99WTjYHX" />
	<Items>
		<DocTemplateItem UniqueId="fdeee583-83a4-4f1f-89e0-ff18720524c9" RuleParameters="PsetName=Pset_SensorTypeCommon;" Order="0">
			<Concepts>
				<DocTemplateUsage Name="Properties" UniqueId="2c49813e-bb78-4a1c-b8d2-6f19c8662173">
					<Definition xsi:type="DocTemplateDefinition" xsi:nil="true" href="Single_Value_1cLVRGAQX7k8yzoVpfoQOW" />
					<Items>
						<DocTemplateItem UniqueId="681c9865-c687-4d63-8528-601c6ef51a5d" RuleParameters="PropertyName=Reference;Value=IfcIdentifier;" Order="0" />
					</Items>
				</DocTemplateUsage>
				<DocTemplateUsage Name="Properties" UniqueId="6c42ff28-42fd-493f-b75a-4baeac1195a0">
					<Definition xsi:type="DocTemplateDefinition" xsi:nil="true" href="Enumerated_Value_31IA2Pmr53g99cNptWj5gL" />
					<Items>
						<DocTemplateItem UniqueId="58e65cfc-311b-4b37-881f-c28c5b57675c" RuleParameters="PropertyName=Status;Value=IfcLabel;" Order="0" />
					</Items>
				</DocTemplateUsage>
			</Concepts>
		</DocTemplateItem>
	</Items>
</DocTemplateUsage>

