<?xml version="1.0" encoding="utf-8"?>
<DocEntity xmlns:xsi="http://www.w3.org/2001/XMLSchema-instance" id="IfcBearingType" Name="IfcBearingType" UniqueId="788924f1-f249-42c4-9da2-6cfbb2519907" DiagramNumber="3" BaseDefinition="IfcBuildingElementType" EntityFlags="32">
	<DiagramRectangle xsi:type="DocRectangle" X="4586.66617838542" Y="79.9999910990397" Width="216" Height="76" />
	<Attributes>
		<DocAttribute Name="PredefinedType" UniqueId="171d3a0d-4025-4c32-95f8-d0ab4958ad07" DefinedType="IfcBearingTypeEnum" AttributeFlags="0" AggregationType="0" AggregationFlag="0">
			<Documentation>Identifies the predefined types of a bearing element from which the type required may be set.</Documentation>
			<DiagramLine>
				<DocPoint X="4802.66617838542" Y="155.99999109904" />
				<DocPoint X="4802.66617838542" Y="247.333333333333" />
				<DocPoint X="8837.33333333333" Y="247.333333333333" />
			</DiagramLine>
			<DiagramLabel xsi:type="DocRectangle" X="4802.66617838542" Y="175.99999109904" Width="400" Height="50" />
		</DocAttribute>
	</Attributes>
	<WhereRules>
		<DocWhereRule Name="CorrectPredefinedType" UniqueId="aac56e07-7991-4014-9e91-aba6e09ff65f">
			<Documentation>The inherited attribute _ElementType_ shall be provided, if the _PredefinedType_ is set to USERDEFINED.</Documentation>
			<Expression>(PredefinedType &lt;&gt; IfcBearingTypeEnum.USERDEFINED) OR
((PredefinedType = IfcBearingTypeEnum.USERDEFINED) AND EXISTS(SELF\IfcElementType.ElementType))</Expression>
		</DocWhereRule>
	</WhereRules>
</DocEntity>

