<?xml version="1.0" encoding="utf-8"?>
<DocTemplateUsage xmlns:xsi="http://www.w3.org/2001/XMLSchema-instance" Name="Property Sets for Objects" UniqueId="4a37912b-7947-4c97-930d-676120a85b6b">
	<Definition xsi:type="DocTemplateDefinition" xsi:nil="true" href="Property_Sets_for_Objects_3tGbMc30vFCOIj99WTjYHX" />
	<Items>
		<DocTemplateItem UniqueId="db5cfade-f235-42b7-b8a2-b2d0b9aeab3a" RuleParameters="Name=Pset_WallCommon;" Order="0">
			<Concepts>
				<DocTemplateUsage Name="Properties" UniqueId="d552f1ef-eb25-4af4-ac99-4b90e2de9841">
					<Definition xsi:type="DocTemplateDefinition" xsi:nil="true" href="Single_Value_1cLVRGAQX7k8yzoVpfoQOW" />
					<Items>
						<DocTemplateItem UniqueId="dc3b504c-3fd9-4666-ac03-62e1653ff13f" RuleParameters="Name=Reference;Value=IfcIdentifier;" Order="0" />
						<DocTemplateItem UniqueId="edfb2154-c24b-4868-8a20-fcc8f3bffaa6" RuleParameters="Name=AcousticRating;Value=IfcLabel;" Order="0" />
						<DocTemplateItem UniqueId="1972b493-c940-49ee-82d8-52b58e997d90" RuleParameters="Name=FireRating;Value=IfcLabel;" Order="0" />
						<DocTemplateItem UniqueId="8153f893-c86f-4730-9895-6829b239c4cf" RuleParameters="Name=Combustible;Value=IfcBoolean;" Order="0" />
						<DocTemplateItem UniqueId="3a32bb30-f746-4250-bd02-66430b830ddf" RuleParameters="Name=SurfaceSpreadOfFlame;Value=IfcLabel;" Order="0" />
						<DocTemplateItem UniqueId="eeaef000-8bf1-4758-8810-ef3ef95c041f" RuleParameters="Name=ThermalTransmittance;Value=IfcThermalTransmittanceMeasure;" Order="0" />
						<DocTemplateItem UniqueId="5fbe2368-95d0-46d7-9e90-91951944947b" RuleParameters="Name=IsExternal;Value=IfcBoolean;" Order="0" />
						<DocTemplateItem UniqueId="8955b524-1431-402d-9b95-e95d57b2c1bc" RuleParameters="Name=ExtendToStructure;Value=IfcBoolean;" Order="0" />
						<DocTemplateItem UniqueId="43c31004-db4a-4105-a76d-ee8ca96ca1c7" RuleParameters="Name=LoadBearing;Value=IfcBoolean;" Order="0" />
						<DocTemplateItem UniqueId="233df661-f8fc-484a-bb0d-f1aa79a47c5d" RuleParameters="Name=Compartmentation;Value=IfcBoolean;" Order="0" />
					</Items>
				</DocTemplateUsage>
				<DocTemplateUsage Name="Properties" UniqueId="98e87ec5-879f-4e94-ad75-16a9d89d325a">
					<Definition xsi:type="DocTemplateDefinition" xsi:nil="true" href="Enumerated_Value_31IA2Pmr53g99cNptWj5gL" />
					<Items>
						<DocTemplateItem UniqueId="3d9a281e-a4da-428d-a42f-00ec68bd8d2e" RuleParameters="Name=Status;Value=IfcLabel;" Order="0" />
					</Items>
				</DocTemplateUsage>
			</Concepts>
		</DocTemplateItem>
	</Items>
</DocTemplateUsage>

