<?xml version="1.0" encoding="utf-8"?>
<DocEntity xmlns:xsi="http://www.w3.org/2001/XMLSchema-instance" id="IfcAirTerminalBoxType" Name="IfcAirTerminalBoxType" UniqueId="bc242f20-3f8e-4532-91aa-3cc02ab65da4" BaseDefinition="IfcFlowControllerType" EntityFlags="101">
	<Localization>
		<DocLocalization Locale="de" Name="Volumenstromregler - Typ" />
		<DocLocalization Locale="en" Name="Air Terminal Box Type" />
		<DocLocalization Locale="fr" Name="Type de diffuseur d&apos;air" />
	</Localization>
	<Attributes>
		<DocAttribute Name="PredefinedType" UniqueId="c02b5e63-acde-4c6c-8b33-c2027b182472" DefinedType="IfcAirTerminalBoxTypeEnum">
			<Documentation>The air terminal box type.</Documentation>
		</DocAttribute>
	</Attributes>
	<WhereRules>
		<DocWhereRule Name="CorrectPredefinedType" UniqueId="6421b41c-a479-45e4-a4f0-c41d8e67a41d">
			<Expression>(PredefinedType &lt;&gt; IfcAirTerminalBoxTypeEnum.USERDEFINED) OR
((PredefinedType = IfcAirTerminalBoxTypeEnum.USERDEFINED) AND EXISTS(SELF\IfcElementType.ElementType))</Expression>
		</DocWhereRule>
	</WhereRules>
</DocEntity>

