<?xml version="1.0" encoding="utf-8"?>
<DocPropertySet xmlns:xsi="http://www.w3.org/2001/XMLSchema-instance" Name="Pset_SensorTypePHSensor" UniqueId="0Jivi0qWOHuO00025QrE$V" ApplicableType="IfcSensor/PHSENSOR" PropertySetType="PSET_TYPEDRIVENOVERRIDE">
	<Localization>
		<DocLocalization Name="Sensor Type PHSensor" Locale="en" />
		<DocLocalization Locale="ja-JP">
			<Documentation>酸性度を感知または検出するデバイス。</Documentation>
		</DocLocalization>
	</Localization>
	<Properties>
		<DocProperty xsi:nil="true" href="SetPointPH_0P4EM0qWOHuO00025QrEV" />
	</Properties>
</DocPropertySet>

