<?xml version="1.0" encoding="utf-8"?>
<DocTemplateUsage xmlns:xsi="http://www.w3.org/2001/XMLSchema-instance" Name="Group Assignment" UniqueId="3Nq78kcTP5tBAvU9I94F7N">
	<Definition xsi:type="DocTemplateDefinition" xsi:nil="true" href="Group_Assignment_3rPvPL9D4sQnHatm9h2M3" />
	<Items>
		<DocTemplateItem UniqueId="41ba50c8-895a-4607-92d5-9fceb58514f5" RuleParameters="Type=IfcDistributionElement;" Order="0">
			<Documentation>Indicates devices that are part of the system, where any ports of the same PredefinedType are considered part of the system implicitly.</Documentation>
		</DocTemplateItem>
		<DocTemplateItem UniqueId="24ea9a22-7779-4c8a-9bfc-c9ca501133a8" RuleParameters="Type=IfcDistributionPort;" Order="0">
			<Documentation>Indicates port that is explicitly part of the system, which overrides any system assignment of the containing device.</Documentation>
		</DocTemplateItem>
	</Items>
</DocTemplateUsage>

