<?xml version="1.0" encoding="utf-8"?>
<DocEntity xmlns:xsi="http://www.w3.org/2001/XMLSchema-instance" id="IfcVoidingFeature" Name="IfcVoidingFeature" UniqueId="76ade710-1f8c-4677-9f36-a21e6d4c7476" DiagramNumber="1" BaseDefinition="IfcFeatureElementSubtraction" EntityFlags="101">
	<Localization>
		<DocLocalization Name="Aussparung / Abzugskörper" Locale="de" />
		<DocLocalization Name="Voiding Feature" Locale="en" />
	</Localization>
	<DiagramRectangle xsi:type="DocRectangle" X="165.80653" Y="1356.1696" Width="317.36771" Height="100" />
	<Attributes>
		<DocAttribute Name="PredefinedType" UniqueId="fff2ddf2-413b-4847-8afd-9e3ed847b801" DefinedType="IfcVoidingFeatureTypeEnum" AttributeFlags="1" AggregationType="0" AggregationFlag="0">
			<Documentation>Qualifies the feature regarding its shape and configuration relative to the voided element.</Documentation>
			<DiagramLine>
				<DocPoint X="483.17424" Y="1406.1696" />
				<DocPoint X="724.5664" Y="1406.1696" />
			</DiagramLine>
			<DiagramLabel xsi:type="DocRectangle" X="483.17424" Y="1406.1696" Width="182" Height="35" />
		</DocAttribute>
	</Attributes>
	<WhereRules>
		<DocWhereRule Name="HasObjectType" UniqueId="38fa8c0a-5f87-41e9-ab2e-b6c484a35713">
			<Documentation>The attribute ObjectType shall be given if the predefined type is set to USERDEFINED.</Documentation>
			<Expression>NOT EXISTS(PredefinedType) OR (PredefinedType &lt;&gt; IfcVoidingFeatureTypeEnum.USERDEFINED) OR EXISTS(SELF\IfcObject.ObjectType)</Expression>
		</DocWhereRule>
	</WhereRules>
</DocEntity>

