<?xml version="1.0" encoding="utf-8"?>
<DocTemplateUsage xmlns:xsi="http://www.w3.org/2001/XMLSchema-instance" Name="Object Typing" UniqueId="49f7ce06-96e5-454f-ac51-3391aed3da00">
	<Definition xsi:type="DocTemplateDefinition" xsi:nil="true" href="Object_Typing_0rek4E8Dz0zAilsiyAPqJq" />
	<Items>
		<DocTemplateItem UniqueId="341387f6-16c0-4161-8ce4-8b148c8d8d11" RuleParameters="RelatingType=IfcVibrationIsolatorType;" Order="0" />
	</Items>
	<Exchanges>
		<DocExchangeItem Applicability="export" Requirement="optional">
			<Exchange xsi:type="DocExchangeDefinition" xsi:nil="true" href="Reference_Exchange_3SsM4bYOvFyBAKwmAlwLEg" />
		</DocExchangeItem>
		<DocExchangeItem Applicability="import" Requirement="optional">
			<Exchange xsi:type="DocExchangeDefinition" xsi:nil="true" href="Reference_Exchange_3SsM4bYOvFyBAKwmAlwLEg" />
		</DocExchangeItem>
	</Exchanges>
</DocTemplateUsage>

