<?xml version="1.0" encoding="utf-8"?>
<DocTemplateUsage xmlns:xsi="http://www.w3.org/2001/XMLSchema-instance" UniqueId="23cf88e8-0cbe-4065-b7ae-e482db6e2bb1">
	<Definition xsi:type="DocTemplateDefinition" xsi:nil="true" href="Property_Sets_for_Objects_3tGbMc30vFCOIj99WTjYHX" />
	<Items>
		<DocTemplateItem UniqueId="b6cb5863-3080-4dff-8b68-754b67570f30" RuleParameters="PsetName=Pset_TankOccurrence;" Order="0">
			<Concepts>
				<DocTemplateUsage Name="Properties" UniqueId="7ca30ba4-3c0d-4abb-b2ea-3b5df6b675d7">
					<Definition xsi:type="DocTemplateDefinition" xsi:nil="true" href="Enumerated_Value_31IA2Pmr53g99cNptWj5gL" />
					<Items>
						<DocTemplateItem UniqueId="1681241a-ae9e-413c-8f7e-3fe412eb4078" RuleParameters="Order=1;PropertyName=TankComposition;Value=IfcLabel;Reference=PEnum_TankComposition" Order="1" />
					</Items>
				</DocTemplateUsage>
				<DocTemplateUsage Name="Properties" UniqueId="5d7c7d8f-4aec-4636-ad71-273badc8ce5c">
					<Definition xsi:type="DocTemplateDefinition" xsi:nil="true" href="Single_Value_1cLVRGAQX7k8yzoVpfoQOW" />
					<Items>
						<DocTemplateItem UniqueId="a5f3e174-4f12-46d5-81de-4c4f2bbd5726" RuleParameters="Order=2;PropertyName=HasLadder;Value=IfcBoolean;" Order="2" />
						<DocTemplateItem UniqueId="bf2f3e6a-6a82-41a9-94dd-406876d934c9" RuleParameters="Order=3;PropertyName=HasVisualIndicator;Value=IfcBoolean;" Order="3" />
					</Items>
				</DocTemplateUsage>
			</Concepts>
		</DocTemplateItem>
		<DocTemplateItem UniqueId="dcb48499-f605-417c-8ba9-3ad42281b858" RuleParameters="PsetName=Pset_TankTypeCommon;" Order="0">
			<Concepts>
				<DocTemplateUsage Name="Properties" UniqueId="275bbcc9-c501-464d-b5c3-533716dadc1e">
					<Definition xsi:type="DocTemplateDefinition" xsi:nil="true" href="Single_Value_1cLVRGAQX7k8yzoVpfoQOW" />
					<Items>
						<DocTemplateItem UniqueId="925393cc-99bf-4a2f-9497-6e68a405d120" RuleParameters="Order=1;PropertyName=Reference;Value=IfcIdentifier;" Order="1" />
						<DocTemplateItem UniqueId="227e5c0e-1922-4287-9b1a-190b346d3b12" RuleParameters="Order=5;PropertyName=NominalLengthOrDiameter;Value=IfcPositiveLengthMeasure;" Order="5" />
						<DocTemplateItem UniqueId="c63711dc-9e15-49c6-8e0c-cea7c1e456dd" RuleParameters="Order=6;PropertyName=NominalWidthOrDiameter;Value=IfcPositiveLengthMeasure;" Order="6" />
						<DocTemplateItem UniqueId="5921cc29-6988-43ef-88a6-a1a35fa98526" RuleParameters="Order=7;PropertyName=NominalDepth;Value=IfcPositiveLengthMeasure;" Order="7" />
						<DocTemplateItem UniqueId="208abb37-1c16-4930-be27-20dd268eb589" RuleParameters="Order=8;PropertyName=NominalCapacity;Value=IfcVolumeMeasure;" Order="8" />
						<DocTemplateItem UniqueId="362f8e4d-2f55-413f-ad7d-97ad1da947aa" RuleParameters="Order=9;PropertyName=EffectiveCapacity;Value=IfcVolumeMeasure;" Order="9" />
						<DocTemplateItem UniqueId="ce7a7e0b-0534-4436-b99a-4cdac2e0b5ee" RuleParameters="Order=10;PropertyName=OperatingWeight;Value=IfcMassMeasure;" Order="10" />
						<DocTemplateItem UniqueId="c1ca8a8f-a285-44ad-a47e-b30651923b23" RuleParameters="Order=13;PropertyName=FirstCurvatureRadius;Value=IfcPositiveLengthMeasure;" Order="13" />
						<DocTemplateItem UniqueId="84b0ebf2-67dc-487e-9720-7dcb75d5e6eb" RuleParameters="Order=14;PropertyName=SecondCurvatureRadius;Value=IfcPositiveLengthMeasure;" Order="14" />
						<DocTemplateItem UniqueId="6f3845eb-f619-4e0a-a055-3555711948eb" RuleParameters="Order=15;PropertyName=NumberOfSections;Value=IfcInteger;" Order="15" />
					</Items>
				</DocTemplateUsage>
				<DocTemplateUsage Name="Properties" UniqueId="da3606ca-31c0-4311-b3e4-6bad71f88300">
					<Definition xsi:type="DocTemplateDefinition" xsi:nil="true" href="Enumerated_Value_31IA2Pmr53g99cNptWj5gL" />
					<Items>
						<DocTemplateItem UniqueId="9728eb46-c9cc-400a-b2e0-31cbd609a776" RuleParameters="Order=2;PropertyName=Status;Value=IfcLabel;Reference=PEnum_ElementStatus" Order="2" />
						<DocTemplateItem UniqueId="8fb32bb1-9c3b-4361-88ef-7f9496e84601" RuleParameters="Order=3;PropertyName=AccessType;Value=IfcLabel;Reference=PEnum_TankAccessType" Order="3" />
						<DocTemplateItem UniqueId="b75c0a5c-a6b1-4bab-ad34-61d4c5db4c60" RuleParameters="Order=4;PropertyName=StorageType;Value=IfcLabel;Reference=PEnum_TankStorageType" Order="4" />
						<DocTemplateItem UniqueId="5d909856-1924-475c-96b1-055d0ddf16d9" RuleParameters="Order=11;PropertyName=PatternType;Value=IfcLabel;Reference=PEnum_TankPatternType" Order="11" />
						<DocTemplateItem UniqueId="e40b9bbe-a551-4d4e-9b46-49d9067cf751" RuleParameters="Order=12;PropertyName=EndShapeType;Value=IfcLabel;Reference=PEnum_EndShapeType" Order="12" />
					</Items>
				</DocTemplateUsage>
			</Concepts>
		</DocTemplateItem>
	</Items>
</DocTemplateUsage>

